{
  "home": [
    {
      "type": "hero",
      "backdropImage": "assets/concept/fangstconcept4.webp",
      "logo": "assets/concept/logo_Fangst_full.svg",
      "actions": [
        {
          "name": "Learn more",
          "url": "/projects"
        },
        {
          "name": "Wishlist",
          "url": ""
        }
      ]
    },
    {
      "type": "carousel",
      "header": "Our projects",
      "headerPosition": "right",
      "class": "toothrack top",
      "images": [
        {
          "url": "assets/projects/LS_Final.webp",
          "header": "Liquid State",
          "link": "/projects"
        },
        {
          "url": "assets/concept/logo_Fangst_full.svg",
          "header": "Fangst",
          "link": "/projects"
        }
      ]
    },
    {
      "type": "text",
      "header": "We are Vertebrae Entertainment",
      "text": "People kept telling us that if we wanted to see people like us in games, we should just make them ourselves. \n\nSo we did!",
      "class": "toothrack top reverse",
      "actions": [],
      "image": {
        "position": "after",
        "url": "assets/asset_slogan.svg"
      }
    },
    {
      "type": "social",
      "header": "Get in touch",
      "headerPosition": "right",
      "class": "toothrack top",
      "links": [
        {
          "name": "Discord",
          "url": "https://discord.gg/b7FpnKtsy3",
          "image": "assets/icons/discord.svg"
        },
        {
          "name": "Twitter",
          "url": "https://twitter.com/vertebraeent",
          "image": "assets/icons/twitter.svg"
        },
        {
          "name": "Tumblr",
          "url": "https://vertebrae-entertainment.tumblr.com/",
          "image": "assets/icons/tumblr.svg"
        },
        {
          "name": "YouTube",
          "url": "https://www.youtube.com/@vertebraeent",
          "image": "assets/icons/youtube.svg"
        },
        {
          "name": "Mail",
          "action": "newsletter",
          "image": "assets/icons/mail.svg"
        }
      ]
    }
  ],
  "about": {},
  "projects": {},
  "linkList": [
    {
      "name": "About us",
      "url": "/about"
    },
    {
      "name": "Our projects",
      "url": "/projects"
    },
    {
      "name": "Devlog",
      "url": "https://vertebrae-entertainment.tumblr.com/"
    },
    {
      "name": "Presskit",
      "url": ""
    }
  ]
}